route_sequence/__init__.py
route_sequence/main.py
route_sequence-0.1.0.dist-info/WHEEL
route_sequence-0.1.0.dist-info/METADATA
route_sequence-0.1.0.dist-info/RECORD
